textconverterim/__init__.py
textconverterim/converter.py
textconverterimp-0.1.5.dist-info/METADATA
textconverterimp-0.1.5.dist-info/WHEEL
textconverterimp-0.1.5.dist-info/top_level.txt
textconverterimp-0.1.5.dist-info/RECORD
