Metadata-Version: 2.1
Name: textconverterimp
Version: 0.1.5
Summary: A library to convert text into different formats.
Author: improve
Author-email: vlasav227@mail.ru
Classifier: Programming Language :: Python :: 3
Classifier: License :: OSI Approved :: MIT License
Classifier: Operating System :: OS Independent
Requires-Python: >=3.6
